cesil/__init__.py
cesil/__main__.py
cesil/cesil.py
cesil/cli.py
cesil-1.0.0.dist-info/METADATA
cesil-1.0.0.dist-info/WHEEL
cesil-1.0.0.dist-info/entry_points.txt
cesil-1.0.0.dist-info/licenses/LICENSE
cesil-1.0.0.dist-info/RECORD
