Metadata-Version: 2.4
Name: cesil
Version: 1.0.0
Summary: CESIL (and CESIL 'Plus') interpreter
Project-URL: Homepage, https://cesil.org
Project-URL: Repository, https://github.com/idunmore/cesil
Author-email: idunmore <62761638+idunmore@users.noreply.github.com>
License-Expression: GPL-3.0-only
License-File: LICENSE
Keywords: ces,cesil,icl,interpreter
Classifier: License :: OSI Approved :: GNU General Public License v3 (GPLv3)
Classifier: Operating System :: OS Independent
Classifier: Programming Language :: Python
Requires-Python: >=3.13
Requires-Dist: click>=8.1.8
